python_redisqueue/python_redisqueue.py
python_redisqueue/__init__.py
python_redisqueue-1.0.3.dist-info/DESCRIPTION.rst
python_redisqueue-1.0.3.dist-info/WHEEL
python_redisqueue-1.0.3.dist-info/RECORD
python_redisqueue-1.0.3.dist-info/METADATA
python_redisqueue-1.0.3.dist-info/top_level.txt
python_redisqueue-1.0.3.dist-info/metadata.json
redisqueue/__init__.py
redisqueue/redisqueue.py
